vivado_bridge/tb/spi_flash_jedec_model.v
module spi_flash_jedec_model #(
    parameter [23:0] JEDEC_ID = 24'h20BA18
) (
    input  wire cs_n,
    input  wire sck,
    input  wire mosi,
    output wire miso
);

    reg [7:0]  cmd_shift = 8'h00;
    reg [2:0]  cmd_bit_count = 3'd0;
    reg [23:0] reply_shift = 24'h000000;
    reg [4:0]  reply_bits_left = 5'd0;
    reg        miso_reg = 1'b0;

    assign miso = miso_reg;

    always @(posedge cs_n) begin
        cmd_shift       <= 8'h00;
        cmd_bit_count   <= 3'd0;
        reply_shift     <= 24'h000000;
        reply_bits_left <= 5'd0;
        miso_reg        <= 1'b0;
    end

    always @(posedge sck) begin
        if (!cs_n) begin
            cmd_shift <= {cmd_shift[6:0], mosi};

            if (cmd_bit_count == 3'd7) begin
                cmd_bit_count <= 3'd0;
                if ({cmd_shift[6:0], mosi} == 8'h9F) begin
                    reply_shift     <= JEDEC_ID;
                    reply_bits_left <= 5'd24;
                end
            end else begin
                cmd_bit_count <= cmd_bit_count + 3'd1;
            end
        end
    end

    always @(negedge sck) begin
        if (!cs_n) begin
            if (reply_bits_left != 5'd0) begin
                miso_reg        <= reply_shift[23];
                reply_shift     <= {reply_shift[22:0], 1'b0};
                reply_bits_left <= reply_bits_left - 5'd1;
            end else begin
                miso_reg <= 1'b0;
            end
        end
    end

endmodule

vivado_bridge/rtl/spi_flash_bridge_core.v
`timescale 1ns/1ps

module spi_flash_bridge_core (
    input  wire        clk,
    input  wire        rst_n,
    input  wire        cmd_valid,
    input  wire [39:0] cmd_word,
    output reg  [39:0] rsp_word,
    output wire        spi_cclk_o,
    output wire        spi_cs_o,
    output wire        spi_io0_o,
    output wire        spi_io0_t,
    input  wire        spi_io1_i,
    output wire        spi_io1_o,
    output wire        spi_io1_t,
    input  wire        spi_io2_i,
    output wire        spi_io2_o,
    output wire        spi_io2_t,
    input  wire        spi_io3_i,
    output wire        spi_io3_o,
    output wire        spi_io3_t
);

    localparam [7:0] CMD_NOP       = 8'h00;
    localparam [7:0] CMD_SET_CS    = 8'h01;
    localparam [7:0] CMD_XFER8     = 8'h02;
    localparam [7:0] CMD_SET_DIV   = 8'h03;
    localparam [7:0] CMD_STATUS    = 8'h04;
    localparam [7:0] CMD_STATUS_EX = 8'h05;
    localparam [7:0] CMD_ECHO      = 8'h06;

    localparam [7:0] ST_OK         = 8'h00;
    localparam [7:0] ST_BUSY       = 8'h01;
    localparam [7:0] ST_BAD_CMD    = 8'hEE;

    localparam [1:0] S_IDLE        = 2'd0;
    localparam [1:0] S_LOW_WAIT    = 2'd1;
    localparam [1:0] S_HIGH_WAIT   = 2'd2;

    reg [1:0]  state      = S_IDLE;
    reg [15:0] clk_div    = 16'd50;
    reg [15:0] wait_cnt   = 16'd0;
    reg [15:0] sck_toggle_count = 16'd0;
    reg [7:0]  tx_shift   = 8'h00;
    reg [7:0]  rx_shift   = 8'h00;
    reg [7:0]  rx_sampled = 8'h00;
    reg [2:0]  bit_index  = 3'd0;

    reg spi_cclk_reg = 1'b0;
    reg spi_cs_reg   = 1'b1;
    reg spi_io0_reg  = 1'b0;
    reg spi_io0_oe   = 1'b0;

    assign spi_cclk_o = spi_cclk_reg;
    assign spi_cs_o   = spi_cs_reg;
    assign spi_io0_o  = spi_io0_reg;
    assign spi_io0_t  = ~spi_io0_oe;

    assign spi_io1_o  = 1'b0;
    assign spi_io1_t  = 1'b1;
    assign spi_io2_o  = 1'b1;
    assign spi_io2_t  = 1'b0;
    assign spi_io3_o  = 1'b1;
    assign spi_io3_t  = 1'b0;

    always @(posedge clk or negedge rst_n) begin
        if (!rst_n) begin
            state            <= S_IDLE;
            clk_div          <= 16'd50;
            wait_cnt         <= 16'd0;
            sck_toggle_count <= 16'd0;
            tx_shift         <= 8'h00;
            rx_shift         <= 8'h00;
            rx_sampled       <= 8'h00;
            bit_index        <= 3'd0;
            spi_cclk_reg     <= 1'b0;
            spi_cs_reg       <= 1'b1;
            spi_io0_reg      <= 1'b0;
            spi_io0_oe       <= 1'b0;
            rsp_word         <= {ST_OK, 8'h00, 8'h00, 8'h00, 8'h00};
        end else begin
            case (state)
                S_IDLE: begin
                    spi_cclk_reg <= 1'b0;

                    if (cmd_valid) begin
                        case (cmd_word[7:0])
                            CMD_NOP: begin
                                rsp_word <= {ST_OK, 8'h00, 8'h00, 8'h00, 8'h00};
                            end

                            CMD_SET_CS: begin
                                spi_cs_reg <= cmd_word[8];
                                rsp_word   <= {ST_OK, 8'h00, 8'h00, 8'h00, {7'h00, cmd_word[8]}};
                            end

                            CMD_SET_DIV: begin
                                clk_div  <= (cmd_word[23:8] == 16'h0000) ? 16'h0001 : cmd_word[23:8];
                                rsp_word <= {ST_OK, 8'h00, 8'h00, cmd_word[23:16], cmd_word[15:8]};
                            end

                            CMD_STATUS: begin
                                rsp_word <= {ST_OK, 8'h00, 8'h00, 8'h00, {5'h00, state != S_IDLE, spi_cclk_reg, spi_cs_reg}};
                            end

                            CMD_STATUS_EX: begin
                                rsp_word <= {
                                    ST_OK,
                                    sck_toggle_count[15:8],
                                    sck_toggle_count[7:0],
                                    {3'b000, state, bit_index},
                                    {2'b00, spi_io3_i, spi_io2_i, spi_io1_i, state != S_IDLE, spi_cclk_reg, spi_cs_reg}
                                };
                            end

                            CMD_ECHO: begin
                                rsp_word <= {
                                    ST_OK,
                                    cmd_word[31:24],
                                    cmd_word[23:16],
                                    cmd_word[15:8],
                                    cmd_word[7:0]
                                };
                            end

                            CMD_XFER8: begin
                                tx_shift    <= cmd_word[15:8];
                                rx_shift    <= 8'h00;
                                rx_sampled  <= 8'h00;
                                bit_index   <= 3'd7;
                                spi_io0_reg <= cmd_word[15];
                                spi_io0_oe  <= 1'b1;
                                wait_cnt    <= clk_div;
                                state       <= S_LOW_WAIT;
                                rsp_word    <= {ST_BUSY, 8'h00, 8'h00, 8'h00, 8'h00};
                            end

                            default: begin
                                rsp_word <= {ST_BAD_CMD, 8'h00, 8'h00, 8'h00, cmd_word[7:0]};
                            end
                        endcase
                    end
                end

                S_LOW_WAIT: begin
                    if (wait_cnt != 16'd0) begin
                        wait_cnt <= wait_cnt - 16'd1;
                    end else begin
                        spi_cclk_reg     <= 1'b1;
                        sck_toggle_count <= sck_toggle_count + 16'd1;
                        rx_shift         <= {rx_shift[6:0], spi_io1_i};
                        rx_sampled       <= {rx_shift[6:0], spi_io1_i};
                        wait_cnt         <= clk_div;
                        state            <= S_HIGH_WAIT;
                    end
                end

                S_HIGH_WAIT: begin
                    if (wait_cnt != 16'd0) begin
                        wait_cnt <= wait_cnt - 16'd1;
                    end else begin
                        spi_cclk_reg     <= 1'b0;
                        sck_toggle_count <= sck_toggle_count + 16'd1;

                        if (bit_index == 3'd0) begin
                            rsp_word <= {ST_OK, 8'h00, 8'h00, 8'h00, rx_sampled};
                            state    <= S_IDLE;
                        end else begin
                            tx_shift    <= {tx_shift[6:0], 1'b0};
                            bit_index   <= bit_index - 3'd1;
                            spi_io0_reg <= tx_shift[6];
                            wait_cnt    <= clk_div;
                            state       <= S_LOW_WAIT;
                        end
                    end
                end

                default: begin
                    state <= S_IDLE;
                end
            endcase
        end
    end

endmodule

vivado_bridge/tb/tb_spi_flash_bridge_core.v
`timescale 1ns/1ps

module tb_spi_flash_bridge_core;

    localparam [7:0] CMD_SET_CS    = 8'h01;
    localparam [7:0] CMD_XFER8     = 8'h02;
    localparam [7:0] CMD_SET_DIV   = 8'h03;
    localparam [7:0] CMD_STATUS_EX = 8'h05;
    localparam [7:0] ST_OK         = 8'h00;
    localparam [7:0] ST_BUSY       = 8'h01;

    reg         clk       = 1'b0;
    reg         rst_n     = 1'b0;
    reg         cmd_valid = 1'b0;
    reg [39:0]  cmd_word  = 40'h0;
    wire [39:0] rsp_word;
    wire        spi_cclk_o;
    wire        spi_cs_o;
    wire        spi_io0_o;
    wire        spi_io0_t;
    wire        spi_io1_i;
    wire        spi_io1_o;
    wire        spi_io1_t;
    wire        spi_io2_o;
    wire        spi_io2_t;
    wire        spi_io3_o;
    wire        spi_io3_t;

    reg         spi_io2_i = 1'b1;
    reg         spi_io3_i = 1'b1;
    reg [7:0]   rx_byte   = 8'h00;
    reg [7:0]   status0   = 8'h00;
    reg [7:0]   status1   = 8'h00;
    reg [7:0]   status2   = 8'h00;
    reg [7:0]   status3   = 8'h00;

    always #5 clk = ~clk;

    spi_flash_bridge_core dut (
        .clk       (clk),
        .rst_n     (rst_n),
        .cmd_valid (cmd_valid),
        .cmd_word  (cmd_word),
        .rsp_word  (rsp_word),
        .spi_cclk_o(spi_cclk_o),
        .spi_cs_o  (spi_cs_o),
        .spi_io0_o (spi_io0_o),
        .spi_io0_t (spi_io0_t),
        .spi_io1_i (spi_io1_i),
        .spi_io1_o (spi_io1_o),
        .spi_io1_t (spi_io1_t),
        .spi_io2_i (spi_io2_i),
        .spi_io2_o (spi_io2_o),
        .spi_io2_t (spi_io2_t),
        .spi_io3_i (spi_io3_i),
        .spi_io3_o (spi_io3_o),
        .spi_io3_t (spi_io3_t)
    );

    spi_flash_jedec_model #(
        .JEDEC_ID(24'h20BA18)
    ) flash_model (
        .cs_n (spi_cs_o),
        .sck  (spi_cclk_o),
        .mosi (spi_io0_o),
        .miso (spi_io1_i)
    );

    initial begin
        $display("Starting tb_spi_flash_bridge_core...");
        $dumpfile("tb_spi_flash_bridge_core.vcd");
        $dumpvars(0, tb_spi_flash_bridge_core);

        repeat (5) @(posedge clk);
        rst_n = 1'b1;
        repeat (5) @(posedge clk);

        send_cmd(CMD_SET_CS, 32'h00000001);
        expect_status("SET_CS high");

        send_cmd(CMD_SET_DIV, 32'h00000002);
        expect_status("SET_DIV");

        send_cmd(CMD_SET_CS, 32'h00000000);
        expect_status("SET_CS low");

        read_status_ex(status0, status1, status2, status3);
        $display("STATUS_EX d0=%02X d1=%02X d2=%02X d3=%02X", status0, status1, status2, status3);

        xfer8(8'h9F, rx_byte);
        $display("CMD 0x9F response byte = 0x%02X", rx_byte);

        xfer8(8'hFF, rx_byte);
        check_byte("JEDEC manufacturer", rx_byte, 8'h20);

        xfer8(8'hFF, rx_byte);
        check_byte("JEDEC memory type", rx_byte, 8'hBA);

        xfer8(8'hFF, rx_byte);
        check_byte("JEDEC capacity", rx_byte, 8'h18);

        send_cmd(CMD_SET_CS, 32'h00000001);
        expect_status("SET_CS high end");

        read_status_ex(status0, status1, status2, status3);
        $display("STATUS_EX end d0=%02X d1=%02X d2=%02X d3=%02X", status0, status1, status2, status3);

        if (spi_io2_o !== 1'b1 || spi_io2_t !== 1'b0 ||
            spi_io3_o !== 1'b1 || spi_io3_t !== 1'b0) begin
            $display("ERROR: IO2/IO3 are not driven high as expected.");
            $fatal(1);
        end

        $display("PASS: bridge core read JEDEC ID 20 BA 18.");
        #100;
        $finish;
    end

    task send_cmd;
        input [7:0] opcode;
        input [31:0] arg;
        begin
            @(posedge clk);
            cmd_word  <= {arg, opcode};
            cmd_valid <= 1'b1;
            @(posedge clk);
            cmd_valid <= 1'b0;
            cmd_word  <= 40'h0;
        end
    endtask

    task expect_status;
        input [8*24-1:0] tag;
        begin
            wait (rsp_word[39:32] == ST_OK);
            @(posedge clk);
            $display("%0s rsp=%02X_%02X_%02X_%02X_%02X",
                     tag,
                     rsp_word[39:32], rsp_word[31:24], rsp_word[23:16],
                     rsp_word[15:8], rsp_word[7:0]);
        end
    endtask

    task xfer8;
        input [7:0] tx_byte;
        output [7:0] rx_out;
        begin
            send_cmd(CMD_XFER8, {24'h0, tx_byte});
            wait (rsp_word[39:32] == ST_BUSY);
            wait (rsp_word[39:32] == ST_OK);
            @(posedge clk);
            rx_out = rsp_word[7:0];
            $display("XFER8 tx=%02X rx=%02X", tx_byte, rx_out);
        end
    endtask

    task read_status_ex;
        output [7:0] d0;
        output [7:0] d1;
        output [7:0] d2;
        output [7:0] d3;
        begin
            send_cmd(CMD_STATUS_EX, 32'h00000000);
            wait (rsp_word[39:32] == ST_OK);
            @(posedge clk);
            d0 = rsp_word[7:0];
            d1 = rsp_word[15:8];
            d2 = rsp_word[23:16];
            d3 = rsp_word[31:24];
        end
    endtask

    task check_byte;
        input [8*24-1:0] tag;
        input [7:0] actual;
        input [7:0] expected;
        begin
            if (actual !== expected) begin
                $display("ERROR: %0s expected 0x%02X got 0x%02X", tag, expected, actual);
                $fatal(1);
            end
        end
    endtask

endmodule

vivado_bridge/sim_out/tb_spi_flash_bridge_core/tb_spi_flash_bridge_core.vcd
$date
   Wed Apr  1 16:21:23 2026
$end
$version
  2018.3
$end
$timescale
  1ps
$end
$scope module tb_spi_flash_bridge_core $end
$var reg 1 ! clk $end
$var reg 1 " rst_n $end
$var reg 1 # cmd_valid $end
$var reg 40 $ cmd_word [39:0] $end
$var wire 40 % rsp_word [39:0] $end
$var wire 1 & spi_cclk_o $end
$var wire 1 ' spi_cs_o $end
$var wire 1 ( spi_io0_o $end
$var wire 1 ) spi_io0_t $end
$var wire 1 * spi_io1_i $end
$var wire 1 + spi_io1_o $end
$var wire 1 , spi_io1_t $end
$var wire 1 - spi_io2_o $end
$var wire 1 . spi_io2_t $end
$var wire 1 / spi_io3_o $end
$var wire 1 0 spi_io3_t $end
$var reg 1 1 spi_io2_i $end
$var reg 1 2 spi_io3_i $end
$var reg 8 3 rx_byte [7:0] $end
$var reg 8 4 status0 [7:0] $end
$var reg 8 5 status1 [7:0] $end
$var reg 8 6 status2 [7:0] $end
$var reg 8 7 status3 [7:0] $end
$var parameter 8 8 CMD_SET_CS [7:0] $end
$var parameter 8 9 CMD_XFER8 [7:0] $end
$var parameter 8 : CMD_SET_DIV [7:0] $end
$var parameter 8 ; CMD_STATUS_EX [7:0] $end
$var parameter 8 < ST_OK [7:0] $end
$var parameter 8 = ST_BUSY [7:0] $end
$scope module dut $end
$var wire 1 > clk $end
$var wire 1 ? rst_n $end
$var wire 1 @ cmd_valid $end
$var wire 40 A cmd_word [39:0] $end
$var reg 40 B rsp_word [39:0] $end
$var wire 1 & spi_cclk_o $end
$var wire 1 ' spi_cs_o $end
$var wire 1 ( spi_io0_o $end
$var wire 1 ) spi_io0_t $end
$var wire 1 * spi_io1_i $end
$var wire 1 + spi_io1_o $end
$var wire 1 , spi_io1_t $end
$var wire 1 C spi_io2_i $end
$var wire 1 - spi_io2_o $end
$var wire 1 . spi_io2_t $end
$var wire 1 D spi_io3_i $end
$var wire 1 / spi_io3_o $end
$var wire 1 0 spi_io3_t $end
$var reg 2 E state [1:0] $end
$var reg 16 F clk_div [15:0] $end
$var reg 16 G wait_cnt [15:0] $end
$var reg 16 H sck_toggle_count [15:0] $end
$var reg 8 I tx_shift [7:0] $end
$var reg 8 J rx_shift [7:0] $end
$var reg 8 K rx_sampled [7:0] $end
$var reg 3 L bit_index [2:0] $end
$var reg 1 M spi_cclk_reg $end
$var reg 1 N spi_cs_reg $end
$var reg 1 O spi_io0_reg $end
$var reg 1 P spi_io0_oe $end
$var parameter 8 Q CMD_NOP [7:0] $end
$var parameter 8 R CMD_SET_CS [7:0] $end
$var parameter 8 S CMD_XFER8 [7:0] $end
$var parameter 8 T CMD_SET_DIV [7:0] $end
$var parameter 8 U CMD_STATUS [7:0] $end
$var parameter 8 V CMD_STATUS_EX [7:0] $end
$var parameter 8 W CMD_ECHO [7:0] $end
$var parameter 8 X ST_OK [7:0] $end
$var parameter 8 Y ST_BUSY [7:0] $end
$var parameter 8 Z ST_BAD_CMD [7:0] $end
$var parameter 2 [ S_IDLE [1:0] $end
$var parameter 2 \ S_LOW_WAIT [1:0] $end
$var parameter 2 ] S_HIGH_WAIT [1:0] $end
$upscope $end
$scope module flash_model $end
$var wire 1 ' cs_n $end
$var wire 1 & sck $end
$var wire 1 ( mosi $end
$var wire 1 * miso $end
$var reg 8 ^ cmd_shift [7:0] $end
$var reg 3 _ cmd_bit_count [2:0] $end
$var reg 24 ` reply_shift [23:0] $end
$var reg 5 a reply_bits_left [4:0] $end
$var reg 1 b miso_reg $end
$var parameter 24 c JEDEC_ID [23:0] $end
$upscope $end
$scope task send_cmd $end
$var reg 8 d opcode [7:0] $end
$var reg 32 e arg [31:0] $end
$upscope $end
$scope task expect_status $end
$var reg 192 f tag [191:0] $end
$upscope $end
$scope task xfer8 $end
$var reg 8 g tx_byte [7:0] $end
$var reg 8 h rx_out [7:0] $end
$upscope $end
$scope task read_status_ex $end
$var reg 8 i d0 [7:0] $end
$var reg 8 j d1 [7:0] $end
$var reg 8 k d2 [7:0] $end
$var reg 8 l d3 [7:0] $end
$upscope $end
$scope task check_byte $end
$var reg 192 m tag [191:0] $end
$var reg 8 n actual [7:0] $end
$var reg 8 o expected [7:0] $end
$upscope $end
$upscope $end
$enddefinitions $end
#0
$dumpvars
0!
0"
0#
b0 $
b0 %
0&
1'
0(
1)
0*
0+
1,
1-
0.
1/
00
11
12
b0 3
b0 4
b0 5
b0 6
b0 7
b1 8
b10 9
b11 :
b101 ;
b0 <
b1 =
0>
0?
0@
b0 A
b0 B
1C
1D
b0 E
b110010 F
b0 G
b0 H
b0 I
b0 J
b0 K
b0 L
0M
1N
0O
0P
b0 Q
b1 R
b10 S
b11 T
b100 U
b101 V
b110 W
b0 X
b1 Y
b11101110 Z
b0 [
b1 \
b10 ]
b0 ^
b0 _
b0 `
b0 a
0b
b1000001011101000011000 c
bx d
bx e
bx f
bx g
bx h
bx i
bx j
bx k
bx l
bx m
bx n
bx o
$end
#5000
1!
1>
#10000
0!
0>
#15000
1!
1>
#20000
0!
0>
#25000
1!
1>
#30000
0!
0>
#35000
1!
1>
#40000
0!
0>
#45000
1!
1"
1>
1?
#50000
0!
0>
#55000
1!
1>
#60000
0!
0>
#65000
1!
1>
#70000
0!
0>
#75000
1!
1>
#80000
0!
0>
#85000
1!
1>
#90000
0!
0>
#95000
1!
1>
b1 d
b1 e
#100000
0!
0>
#105000
1!
1#
b100000001 $
1>
1@
b100000001 A
#110000
0!
0>
#115000
1!
0#
b0 $
b1 %
1>
0@
b0 A
b1 B
b101001101000101010101000101111101000011010100110010000001101000011010010110011101101000 f
#120000
0!
0>
#125000
1!
1>
b11 d
b10 e
#130000
0!
0>
#135000
1!
1#
b1000000011 $
1>
1@
b1000000011 A
#140000
0!
0>
#145000
1!
0#
b0 $
b10 %
1>
0@
b0 A
b10 B
b10 F
b1010011010001010101010001011111010001000100100101010110 f
#150000
0!
0>
#155000
1!
1>
b1 d
b0 e
#160000
0!
0>
#165000
1!
1#
b1 $
1>
1@
b1 A
#170000
0!
0>
#175000
1!
0#
b0 $
b0 %
0'
1>
0@
b0 A
b0 B
0N
b1010011010001010101010001011111010000110101001100100000011011000110111101110111 f
#180000
0!
0>
#185000
1!
1>
b101 d
#190000
0!
0>
#195000
1!
1#
b101 $
1>
1@
b101 A
#200000
0!
0>
#205000
1!
0#
b0 $
b110000 %
1>
0@
b0 A
b110000 B
#210000
0!
0>
#215000
1!
b110000 4
1>
b10 d
b10011111 e
b10011111 g
b110000 i
b0 j
b0 k
b0 l
#220000
0!
0>
#225000
1!
1#
b1001111100000010 $
1>
1@
b1001111100000010 A
#230000
0!
0>
#235000
1!
0#
b0 $
b100000000000000000000000000000000 %
1(
0)
1>
0@
b0 A
b100000000000000000000000000000000 B
b1 E
b10 G
b10011111 I
b111 L
1O
1P
#240000
0!
0>
#245000
1!
1>
b1 G
#250000
0!
0>
#255000
1!
1>
b0 G
#260000
0!
0>
#265000
1!
1&
1>
b10 E
b10 G
b1 H
1M
b1 ^
b1 _
#270000
0!
0>
#275000
1!
1>
b1 G
#280000
0!
0>
#285000
1!
1>
b0 G
#290000
0!
0>
#295000
1!
0&
0(
1>
b1 E
b10 G
b10 H
b111110 I
b110 L
0M
0O
#300000
0!
0>
#305000
1!
1>
b1 G
#310000
0!
0>
#315000
1!
1>
b0 G
#320000
0!
0>
#325000
1!
1&
1>
b10 E
b10 G
b11 H
1M
b10 ^
b10 _
#330000
0!
0>
#335000
1!
1>
b1 G
#340000
0!
0>
#345000
1!
1>
b0 G
#350000
0!
0>
#355000
1!
0&
1>
b1 E
b10 G
b100 H
b1111100 I
b101 L
0M
#360000
0!
0>
#365000
1!
1>
b1 G
#370000
0!
0>
#375000
1!
1>
b0 G
#380000
0!
0>
#385000
1!
1&
1>
b10 E
b10 G
b101 H
1M
b100 ^
b11 _
#390000
0!
0>
#395000
1!
1>
b1 G
#400000
0!
0>
#405000
1!
1>
b0 G
#410000
0!
0>
#415000
1!
0&
1(
1>
b1 E
b10 G
b110 H
b11111000 I
b100 L
0M
1O
#420000
0!
0>
#425000
1!
1>
b1 G
#430000
0!
0>
#435000
1!
1>
b0 G
#440000
0!
0>
#445000
1!
1&
1>
b10 E
b10 G
b111 H
1M
b1001 ^
b100 _
#450000
0!
0>
#455000
1!
1>
b1 G
#460000
0!
0>
#465000
1!
1>
b0 G
#470000
0!
0>
#475000
1!
0&
1>
b1 E
b10 G
b1000 H
b11110000 I
b11 L
0M
#480000
0!
0>
#485000
1!
1>
b1 G
#490000
0!
0>
#495000
1!
1>
b0 G
#500000
0!
0>
#505000
1!
1&
1>
b10 E
b10 G
b1001 H
1M
b10011 ^
b101 _
#510000
0!
0>
#515000
1!
1>
b1 G
#520000
0!
0>
#525000
1!
1>
b0 G
#530000
0!
0>
#535000
1!
0&
1>
b1 E
b10 G
b1010 H
b11100000 I
b10 L
0M
#540000
0!
0>
#545000
1!
1>
b1 G
#550000
0!
0>
#555000
1!
1>
b0 G
#560000
0!
0>
#565000
1!
1&
1>
b10 E
b10 G
b1011 H
1M
b100111 ^
b110 _
#570000
0!
0>
#575000
1!
1>
b1 G
#580000
0!
0>
#585000
1!
1>
b0 G
#590000
0!
0>
#595000
1!
0&
1>
b1 E
b10 G
b1100 H
b11000000 I
b1 L
0M
#600000
0!
0>
#605000
1!
1>
b1 G
#610000
0!
0>
#615000
1!
1>
b0 G
#620000
0!
0>
#625000
1!
1&
1>
b10 E
b10 G
b1101 H
1M
b1001111 ^
b111 _
#630000
0!
0>
#635000
1!
1>
b1 G
#640000
0!
0>
#645000
1!
1>
b0 G
#650000
0!
0>
#655000
1!
0&
1>
b1 E
b10 G
b1110 H
b10000000 I
b0 L
0M
#660000
0!
0>
#665000
1!
1>
b1 G
#670000
0!
0>
#675000
1!
1>
b0 G
#680000
0!
0>
#685000
1!
1&
1>
b10 E
b10 G
b1111 H
1M
b10011111 ^
b0 _
b1000001011101000011000 `
b11000 a
#690000
0!
0>
#695000
1!
1>
b1 G
#700000
0!
0>
#705000
1!
1>
b0 G
#710000
0!
0>
#715000
1!
b0 %
0&
1>
b0 B
b0 E
b10000 H
0M
b10000010111010000110000 `
b10111 a
#720000
0!
0>
#725000
1!
1>
b11111111 e
b11111111 g
b0 h
#730000
0!
0>
#735000
1!
1#
b1111111100000010 $
1>
1@
b1111111100000010 A
#740000
0!
0>
#745000
1!
0#
b0 $
b100000000000000000000000000000000 %
1>
0@
b0 A
b100000000000000000000000000000000 B
b1 E
b10 G
b11111111 I
b111 L
#750000
0!
0>
#755000
1!
1>
b1 G
#760000
0!
0>
#765000
1!
1>
b0 G
#770000
0!
0>
#775000
1!
1&
1>
b10 E
b10 G
b10001 H
1M
b111111 ^
b1 _
#780000
0!
0>
#785000
1!
1>
b1 G
#790000
0!
0>
#795000
1!
1>
b0 G
#800000
0!
0>
#805000
1!
0&
1>
b1 E
b10 G
b10010 H
b11111110 I
b110 L
0M
b100000101110100001100000 `
b10110 a
#810000
0!
0>
#815000
1!
1>
b1 G
#820000
0!
0>
#825000
1!
1>
b0 G
#830000
0!
0>
#835000
1!
1&
1>
b10 E
b10 G
b10011 H
1M
b1111111 ^
b10 _
#840000
0!
0>
#845000
1!
1>
b1 G
#850000
0!
0>
#855000
1!
1>
b0 G
#860000
0!
0>
#865000
1!
0&
1*
1>
b1 E
b10 G
b10100 H
b11111100 I
b101 L
0M
b1011101000011000000 `
b10101 a
1b
#870000
0!
0>
#875000
1!
1>
b1 G
#880000
0!
0>
#885000
1!
1>
b0 G
#890000
0!
0>
#895000
1!
1&
1>
b10 E
b10 G
b10101 H
b1 J
b1 K
1M
b11111111 ^
b11 _
#900000
0!
0>
#905000
1!
1>
b1 G
#910000
0!
0>
#915000
1!
1>
b0 G
#920000
0!
0>
#925000
1!
0&
0*
1>
b1 E
b10 G
b10110 H
b11111000 I
b100 L
0M
b10111010000110000000 `
b10100 a
0b
#930000
0!
0>
#935000
1!
1>
b1 G
#940000
0!
0>
#945000
1!
1>
b0 G
#950000
0!
0>
#955000
1!
1&
1>
b10 E
b10 G
b10111 H
b10 J
b10 K
1M
b100 _
#960000
0!
0>
#965000
1!
1>
b1 G
#970000
0!
0>
#975000
1!
1>
b0 G
#980000
0!
0>
#985000
1!
0&
1>
b1 E
b10 G
b11000 H
b11110000 I
b11 L
0M
b101110100001100000000 `
b10011 a
#990000
0!
0>
#995000
1!
1>
b1 G
#1000000
0!
0>
#1005000
1!
1>
b0 G
#1010000
0!
0>
#1015000
1!
1&
1>
b10 E
b10 G
b11001 H
b100 J
b100 K
1M
b101 _
#1020000
0!
0>
#1025000
1!
1>
b1 G
#1030000
0!
0>
#1035000
1!
1>
b0 G
#1040000
0!
0>
#1045000
1!
0&
1>
b1 E
b10 G
b11010 H
b11100000 I
b10 L
0M
b1011101000011000000000 `
b10010 a
#1050000
0!
0>
#1055000
1!
1>
b1 G
#1060000
0!
0>
#1065000
1!
1>
b0 G
#1070000
0!
0>
#1075000
1!
1&
1>
b10 E
b10 G
b11011 H
b1000 J
b1000 K
1M
b110 _
#1080000
0!
0>
#1085000
1!
1>
b1 G
#1090000
0!
0>
#1095000
1!
1>
b0 G
#1100000
0!
0>
#1105000
1!
0&
1>
b1 E
b10 G
b11100 H
b11000000 I
b1 L
0M
b10111010000110000000000 `
b10001 a
#1110000
0!
0>
#1115000
1!
1>
b1 G
#1120000
0!
0>
#1125000
1!
1>
b0 G
#1130000
0!
0>
#1135000
1!
1&
1>
b10 E
b10 G
b11101 H
b10000 J
b10000 K
1M
b111 _
#1140000
0!
0>
#1145000
1!
1>
b1 G
#1150000
0!
0>
#1155000
1!
1>
b0 G
#1160000
0!
0>
#1165000
1!
0&
1>
b1 E
b10 G
b11110 H
b10000000 I
b0 L
0M
b101110100001100000000000 `
b10000 a
#1170000
0!
0>
#1175000
1!
1>
b1 G
#1180000
0!
0>
#1185000
1!
1>
b0 G
#1190000
0!
0>
#1195000
1!
1&
1>
b10 E
b10 G
b11111 H
b100000 J
b100000 K
1M
b0 _
#1200000
0!
0>
#1205000
1!
1>
b1 G
#1210000
0!
0>
#1215000
1!
1>
b0 G
#1220000
0!
0>
#1225000
1!
b100000 %
0&
1*
1>
b100000 B
b0 E
b100000 H
0M
b11101000011000000000000 `
b1111 a
1b
#1230000
0!
0>
#1235000
1!
b100000 3
1>
b100000 h
b10010100100010101000100010001010100001100100000011011010110000101101110011101010110011001100001011000110111010001110101011100100110010101110010 m
b100000 n
b100000 o
#1240000
0!
0>
#1245000
1!
1#
b1111111100000010 $
1>
1@
b1111111100000010 A
#1250000
0!
0>
#1255000
1!
0#
b0 $
b100000000000000000000000000000000 %
1>
0@
b0 A
b100000000000000000000000000000000 B
b1 E
b10 G
b11111111 I
b0 J
b0 K
b111 L
#1260000
0!
0>
#1265000
1!
1>
b1 G
#1270000
0!
0>
#1275000
1!
1>
b0 G
#1280000
0!
0>
#1285000
1!
1&
1>
b10 E
b10 G
b100001 H
b1 J
b1 K
1M
b1 _
#1290000
0!
0>
#1295000
1!
1>
b1 G
#1300000
0!
0>
#1305000
1!
1>
b0 G
#1310000
0!
0>
#1315000
1!
0&
0*
1>
b1 E
b10 G
b100010 H
b11111110 I
b110 L
0M
b111010000110000000000000 `
b1110 a
0b
#1320000
0!
0>
#1325000
1!
1>
b1 G
#1330000
0!
0>
#1335000
1!
1>
b0 G
#1340000
0!
0>
#1345000
1!
1&
1>
b10 E
b10 G
b100011 H
b10 J
b10 K
1M
b10 _
#1350000
0!
0>
#1355000
1!
1>
b1 G
#1360000
0!
0>
#1365000
1!
1>
b0 G
#1370000
0!
0>
#1375000
1!
0&
1*
1>
b1 E
b10 G
b100100 H
b11111100 I
b101 L
0M
b110100001100000000000000 `
b1101 a
1b
#1380000
0!
0>
#1385000
1!
1>
b1 G
#1390000
0!
0>
#1395000
1!
1>
b0 G
#1400000
0!
0>
#1405000
1!
1&
1>
b10 E
b10 G
b100101 H
b101 J
b101 K
1M
b11 _
#1410000
0!
0>
#1415000
1!
1>
b1 G
#1420000
0!
0>
#1425000
1!
1>
b0 G
#1430000
0!
0>
#1435000
1!
0&
1>
b1 E
b10 G
b100110 H
b11111000 I
b100 L
0M
b101000011000000000000000 `
b1100 a
#1440000
0!
0>
#1445000
1!
1>
b1 G
#1450000
0!
0>
#1455000
1!
1>
b0 G
#1460000
0!
0>
#1465000
1!
1&
1>
b10 E
b10 G
b100111 H
b1011 J
b1011 K
1M
b100 _
#1470000
0!
0>
#1475000
1!
1>
b1 G
#1480000
0!
0>
#1485000
1!
1>
b0 G
#1490000
0!
0>
#1495000
1!
0&
1>
b1 E
b10 G
b101000 H
b11110000 I
b11 L
0M
b10000110000000000000000 `
b1011 a
#1500000
0!
0>
#1505000
1!
1>
b1 G
#1510000
0!
0>
#1515000
1!
1>
b0 G
#1520000
0!
0>
#1525000
1!
1&
1>
b10 E
b10 G
b101001 H
b10111 J
b10111 K
1M
b101 _
#1530000
0!
0>
#1535000
1!
1>
b1 G
#1540000
0!
0>
#1545000
1!
1>
b0 G
#1550000
0!
0>
#1555000
1!
0&
0*
1>
b1 E
b10 G
b101010 H
b11100000 I
b10 L
0M
b100001100000000000000000 `
b1010 a
0b
#1560000
0!
0>
#1565000
1!
1>
b1 G
